gym_robotorydownscale/__init__.py
gym_robotorydownscale/envs/__init__.py
gym_robotorydownscale/envs/robotorydownscale_env.py
gym_robotorydownscale-0.0.1.dist-info/METADATA
gym_robotorydownscale-0.0.1.dist-info/WHEEL
gym_robotorydownscale-0.0.1.dist-info/top_level.txt
gym_robotorydownscale-0.0.1.dist-info/RECORD
